{"cameraMode":{"drawMode":0,"name":"Shaded","section":"Shading Mode"},"sceneLighting":false,"audioPlay":false,"sceneViewState":{"showFog":true,"showMaterialUpdate":false,"showSkybox":false,"showFlares":true,"showImageEffects":false,"showParticleSystems":true,"showVisualEffectGraphs":true,"m_FxEnabled":true},"in2DMode":false,"pivot":{"x":-1.257312297821045,"y":-0.6237714290618897,"z":-2.6358509063720705},"rotation":{"x":0.0104130944237113,"y":0.9808858036994934,"z":-0.18641658127307893,"w":0.054790958762168887},"size":3.0322890281677248,"orthographic":false}