{"cameraMode":{"drawMode":0,"name":"Shaded","section":"Shading Mode"},"sceneLighting":false,"audioPlay":false,"sceneViewState":{"showFog":true,"showMaterialUpdate":false,"showSkybox":false,"showFlares":true,"showImageEffects":false,"showParticleSystems":true,"showVisualEffectGraphs":true,"m_FxEnabled":true},"in2DMode":false,"pivot":{"x":-0.7031271457672119,"y":-2.3837168216705324,"z":9.614742279052735},"rotation":{"x":0.12252221256494522,"y":-0.05207889899611473,"z":0.006435805466026068,"w":0.9910833835601807},"size":5.705017566680908,"orthographic":false}